h4ck/__init__.py
h4ck/h4ck.py
h4ck-0.0.1.dist-info/LICENSE
h4ck-0.0.1.dist-info/METADATA
h4ck-0.0.1.dist-info/WHEEL
h4ck-0.0.1.dist-info/top_level.txt
h4ck-0.0.1.dist-info/RECORD
