Metadata-Version: 2.1
Name: h4ck
Version: 0.0.1
Summary: A simple library that prints a greeting.
Home-page: https://github.com/im-yellow/Y_ellow/
Author: Y-ellow
Author-email: im.yellow.dev@gmail.com
Classifier: Programming Language :: Python :: 3
Classifier: License :: OSI Approved :: MIT License
Classifier: Operating System :: OS Independent
Requires-Python: >=3.6
License-File: LICENSE
